dask_yarn/__init__.py
dask_yarn/core.py
knit/__init__.py
knit/compatibility.py
knit/conf.py
knit/core.py
knit/env.py
knit/exceptions.py
knit/utils.py
knit/yarn_api.py
knit/java_libs/knit-1.0-SNAPSHOT.jar
knit-0.2.4.dist-info/DESCRIPTION.rst
knit-0.2.4.dist-info/METADATA
knit-0.2.4.dist-info/RECORD
knit-0.2.4.dist-info/WHEEL
knit-0.2.4.dist-info/metadata.json
knit-0.2.4.dist-info/top_level.txt
