Metadata-Version: 2.0
Name: knit
Version: 0.2.4
Summary: Python wrapper for YARN Applications
Home-page: http://github.com/dask/knit/
Author: Benjamin Zaitlen
Author-email: bzaitlen@anaconda.com
License: BSD
Keywords: yarn
Platform: UNKNOWN
Requires-Dist: py4j
Requires-Dist: requests
